{
  "timestamp": "2026-06-15T08:30:26.130Z",
  "collectionTime": 70807,
  "data": {
    "exchange": {
      "usdToKrw": 1513,
      "eurToKrw": 1756.44,
      "jpyToKrw": 945.09,
      "cnyToKrw": 223.89,
      "timestamp": "2026-06-15"
    },
    "expandedExchange": {
      "major": {
        "usdToKrw": 1513,
        "eurToKrw": 1756.44,
        "jpyToKrw": 945.09,
        "cnyToKrw": 223.89,
        "gbpToKrw": 2032.64,
        "chfToKrw": 1907.82,
        "audToKrw": 1070.45,
        "cadToKrw": 1082.96
      },
      "asia": {
        "sgdToKrw": 1180.69,
        "hkdToKrw": 193.09,
        "twdToKrw": 47.98,
        "thbToKrw": 46.46,
        "vndToKrw": 5.76,
        "phpToKrw": 25.05,
        "myrToKrw": 373.58,
        "idrToKrw": 8.55
      },
      "units": {
        "JPY": 100,
        "VND": 100,
        "IDR": 10000
      },
      "timestamp": "2026-06-15"
    },
    "crypto": {
      "binancecoin": {
        "usd": 615.43,
        "krw": 931084,
        "change24h": "0.77",
        "marketCap": 82940137042.50496
      },
      "bitcoin": {
        "usd": 65625,
        "krw": 99282802,
        "change24h": "1.86",
        "marketCap": 1315526335169.1663
      },
      "cardano": {
        "usd": 0.180268,
        "krw": 272.77,
        "change24h": "5.30",
        "marketCap": 6705931367.115799
      },
      "dogecoin": {
        "usd": 0.088565,
        "krw": 134.01,
        "change24h": "1.45",
        "marketCap": 13686438961.070885
      },
      "ethereum": {
        "usd": 1717.45,
        "krw": 2598319,
        "change24h": "2.43",
        "marketCap": 207274018715.92838
      },
      "polkadot": {
        "usd": 1.001,
        "krw": 1515.13,
        "change24h": "3.22",
        "marketCap": 1690618813.655082
      },
      "ripple": {
        "usd": 1.18,
        "krw": 1784.2,
        "change24h": "2.86",
        "marketCap": 73171858981.50836
      },
      "solana": {
        "usd": 71.3,
        "krw": 107867,
        "change24h": "4.43",
        "marketCap": 41347728299.54812
      }
    },
    "expandedCrypto": {
      "avalanche-2": {
        "usd": 6.76,
        "usd_market_cap": 2920319409.921599,
        "usd_24h_vol": 182993452.13125694,
        "usd_24h_change": 1.531132700538334,
        "krw": 10234.16,
        "krw_market_cap": 4418798728489.956,
        "krw_24h_vol": 276891367037.5852,
        "krw_24h_change": 1.203516518482527
      },
      "binancecoin": {
        "usd": 615.43,
        "usd_market_cap": 82940137042.50496,
        "usd_24h_vol": 808971470.1095016,
        "usd_24h_change": 0.7734513498225599,
        "krw": 931084,
        "krw_market_cap": 125498522818790.86,
        "krw_24h_vol": 1223886328640.7256,
        "krw_24h_change": 0.43301888566845476
      },
      "bitcoin": {
        "usd": 65625,
        "usd_market_cap": 1315526335169.1663,
        "usd_24h_vol": 25842160392.65814,
        "usd_24h_change": 1.8646455329964224,
        "krw": 99282802,
        "krw_market_cap": 1990551470976465.5,
        "krw_24h_vol": 39096393353444.24,
        "krw_24h_change": 1.5205268010835928
      },
      "bitcoin-cash": {
        "usd": 212.9,
        "usd_market_cap": 4268022696.754939,
        "usd_24h_vol": 142727536.64386865,
        "usd_24h_change": 4.425219328324717,
        "krw": 322150,
        "krw_market_cap": 6458037843912.873,
        "krw_24h_vol": 215964135737.93362,
        "krw_24h_change": 4.088264635151029
      },
      "cardano": {
        "usd": 0.180268,
        "usd_market_cap": 6705931367.115799,
        "usd_24h_vol": 539201070.6669896,
        "usd_24h_change": 5.2968951060824905,
        "krw": 272.77,
        "krw_market_cap": 10146890404412.209,
        "krw_24h_vol": 815876851473.4769,
        "krw_24h_change": 4.957127727945048
      },
      "chainlink": {
        "usd": 8.19,
        "usd_market_cap": 5952223852.788862,
        "usd_24h_vol": 193225756.89231727,
        "usd_24h_change": 3.426000598708736,
        "krw": 12386.27,
        "krw_market_cap": 9006439193956.912,
        "krw_24h_vol": 292329669141.1787,
        "krw_24h_change": 3.0766073034528736
      },
      "dogecoin": {
        "usd": 0.088565,
        "usd_market_cap": 13686438961.070885,
        "usd_24h_vol": 737708358.0250676,
        "usd_24h_change": 1.4493832007005054,
        "krw": 134.01,
        "krw_market_cap": 20709248061450.586,
        "krw_24h_vol": 1116242539553.2664,
        "krw_24h_change": 1.1220308043260967
      },
      "ethereum": {
        "usd": 1717.45,
        "usd_market_cap": 207274018715.92838,
        "usd_24h_vol": 9572503489.257019,
        "usd_24h_change": 2.4329080030828543,
        "krw": 2598319,
        "krw_market_cap": 313630819710757.75,
        "krw_24h_vol": 14482162331115.94,
        "krw_24h_change": 2.086869569201034
      },
      "litecoin": {
        "usd": 45.17,
        "usd_market_cap": 3489317748.2581863,
        "usd_24h_vol": 225494922.90547296,
        "usd_24h_change": 2.4914943779037433,
        "krw": 68340,
        "krw_market_cap": 5279762472870.954,
        "krw_24h_vol": 341149426795.6648,
        "krw_24h_change": 2.1452580277684024
      },
      "monero": {
        "usd": 335.11,
        "usd_market_cap": 6276790452.645164,
        "usd_24h_vol": 112741176.83353472,
        "usd_24h_change": -1.1486969640640192,
        "krw": 507058,
        "krw_market_cap": 9497547965786.03,
        "krw_24h_vol": 170591123405.18225,
        "krw_24h_change": -1.4676659899232545
      },
      "polkadot": {
        "usd": 1.001,
        "usd_market_cap": 1690618813.655082,
        "usd_24h_vol": 96379415.55507785,
        "usd_24h_change": 3.2211364567719807,
        "krw": 1515.13,
        "krw_market_cap": 2558112047182.138,
        "krw_24h_vol": 145833787037.2942,
        "krw_24h_change": 2.888067045115069
      },
      "ripple": {
        "usd": 1.18,
        "usd_market_cap": 73171858981.50836,
        "usd_24h_vol": 1519638398.5202975,
        "usd_24h_change": 2.8579362160262503,
        "krw": 1784.2,
        "krw_market_cap": 110717929117697.36,
        "krw_24h_vol": 2299048519195.2803,
        "krw_24h_change": 2.510461953561321
      },
      "shiba-inu": {
        "usd": 0.000005,
        "usd_market_cap": 2943817369.7234716,
        "usd_24h_vol": 84814027.91374168,
        "usd_24h_change": -0.2778044551312402,
        "krw": 0.00755888,
        "krw_market_cap": 4454354001841.856,
        "krw_24h_vol": 128333947796.96886,
        "krw_24h_change": -0.5995836385369346
      },
      "solana": {
        "usd": 71.3,
        "usd_market_cap": 41347728299.54812,
        "usd_24h_vol": 1953684463.5718932,
        "usd_24h_change": 4.431191722632778,
        "krw": 107867,
        "krw_market_cap": 62564145762704.914,
        "krw_24h_vol": 2955713265289.534,
        "krw_24h_change": 4.078402694803733
      },
      "stellar": {
        "usd": 0.189927,
        "usd_market_cap": 6398990236.177367,
        "usd_24h_vol": 186395479.98759067,
        "usd_24h_change": 1.7849051903528197,
        "krw": 287.38,
        "krw_market_cap": 9682451112427.904,
        "krw_24h_vol": 282039049279.0489,
        "krw_24h_change": 1.4564701464168148
      },
      "tether": {
        "usd": 0.999278,
        "usd_market_cap": 186425817799.65695,
        "usd_24h_vol": 43939990616.57729,
        "usd_24h_change": -0.015274051643192966,
        "krw": 1511.8,
        "krw_market_cap": 282084954081423.4,
        "krw_24h_vol": 66476452858036.44,
        "krw_24h_change": -0.3530420468486959
      },
      "the-open-network": {
        "usd": 1.8,
        "usd_market_cap": 4836989503.141211,
        "usd_24h_vol": 174565392.43588465,
        "usd_24h_change": 4.777649431264753,
        "krw": 2729.18,
        "krw_market_cap": 7318953876614.975,
        "krw_24h_vol": 264138686855.06085,
        "krw_24h_change": 4.439557532175062
      },
      "tron": {
        "usd": 0.32005,
        "usd_market_cap": 30349945670.757923,
        "usd_24h_vol": 540167784.2977316,
        "usd_24h_change": 0.9720985233864501,
        "krw": 484.27,
        "krw_market_cap": 45923161995243.8,
        "krw_24h_vol": 817339606865.1729,
        "krw_24h_change": 0.6462862081632668
      },
      "uniswap": {
        "usd": 2.61,
        "usd_market_cap": 1622387844.6963649,
        "usd_24h_vol": 101491852.17829153,
        "usd_24h_change": 2.746925321006881,
        "krw": 3946.82,
        "krw_market_cap": 2454870286074.057,
        "krw_24h_vol": 153569525934.00226,
        "krw_24h_change": 2.4153860729328636
      }
    },
    "kospi": {
      "value": 8545.98,
      "change": "5.20",
      "changeAmount": "422.36",
      "timestamp": "2026-06-15T08:30:45.186Z",
      "source": "yahoo"
    },
    "kosdaq": {
      "value": 1034.03,
      "change": "3.72",
      "changeAmount": "37.10",
      "timestamp": "2026-06-15T08:30:45.241Z",
      "source": "yahoo"
    },
    "nasdaq": null,
    "globalIndices": {
      "dji": {
        "name": "다우존스",
        "value": 51202.26,
        "previousClose": 50848.75,
        "change": "0.00",
        "symbol": "DJI",
        "source": "naver"
      },
      "nasdaq": {
        "name": "나스닥",
        "value": 25888.84,
        "previousClose": 25809.66,
        "change": "0.00",
        "symbol": "NASDAQ",
        "source": "naver"
      },
      "gspc": {
        "name": "S&P 500",
        "value": 7431.46,
        "previousClose": 7394.3,
        "change": "0.00",
        "symbol": "GSPC",
        "source": "naver"
      },
      "n225": {
        "name": "닛케이 225",
        "value": 69317.5,
        "previousClose": 66020.04,
        "change": "0.00",
        "symbol": "N225",
        "source": "naver"
      },
      "000001ss": {
        "name": "상해종합",
        "value": 4096.47,
        "previousClose": 4031.51,
        "change": "0.00",
        "symbol": "000001SS",
        "source": "naver"
      },
      "hsi": {
        "name": "항셍지수",
        "value": 24842.67,
        "previousClose": 24718.1,
        "change": "0.00",
        "symbol": "HSI",
        "source": "naver"
      },
      "gdaxi": {
        "name": "DAX",
        "value": 24994.12,
        "previousClose": 24635.3,
        "change": "0.00",
        "symbol": "GDAXI",
        "source": "naver"
      },
      "fchi": {
        "name": "CAC 40",
        "value": 8445.41,
        "previousClose": 8350.869999999999,
        "change": "0.00",
        "symbol": "FCHI",
        "source": "naver"
      },
      "rut": {
        "name": "러셀 2000",
        "value": 2943.992,
        "previousClose": 2921.03,
        "change": "0.79",
        "symbol": "^RUT",
        "source": "yahoo"
      },
      "ftse": {
        "name": "FTSE 100",
        "value": 10505.59,
        "previousClose": 10471.72,
        "change": "0.32",
        "symbol": "^FTSE",
        "source": "yahoo"
      }
    },
    "commodities": {
      "gold": {
        "price": 4329.25,
        "unit": "USD/oz",
        "change": "107.25"
      },
      "silver": {
        "price": 70.375,
        "unit": "USD/oz",
        "change": "2.614"
      },
      "copper": {
        "price": 6.5051,
        "unit": "USD/lb",
        "change": "0.0746"
      },
      "oil": {
        "wti": null,
        "brent": 83.024,
        "unit": "USD/bbl",
        "change": "4.306"
      }
    },
    "expandedCommodities": {
      "oil_brent": {
        "price": 83.024,
        "unit": "USD/bbl",
        "name": "브렌트유",
        "change": "4.306"
      },
      "gasoline": {
        "price": 2.9226,
        "unit": "USD/gal",
        "name": "휘발유",
        "change": "0.1272"
      },
      "gold": {
        "price": 4329.25,
        "unit": "USD/oz",
        "name": "금",
        "change": "107.25"
      },
      "silver": {
        "price": 70.375,
        "unit": "USD/oz",
        "name": "은",
        "change": "2.614"
      },
      "copper": {
        "price": 6.5051,
        "unit": "USD/lb",
        "name": "구리",
        "change": "0.0746"
      },
      "platinum": {
        "price": 1779.3,
        "unit": "USD/oz",
        "name": "백금",
        "change": "67.10"
      },
      "soybeans": {
        "price": 1109.52,
        "unit": "USD/부셸",
        "name": "대두",
        "change": "3.98"
      },
      "wheat": {
        "price": 573.22,
        "unit": "USD/부셸",
        "name": "밀",
        "change": "11.28"
      },
      "coffee": {
        "price": 253.22,
        "unit": "USc/lb",
        "name": "커피",
        "change": "0.18"
      },
      "cotton": {
        "price": 76.269,
        "unit": "USc/lb",
        "name": "면화",
        "change": "0.151"
      },
      "rice": {
        "price": 12.04,
        "unit": "USD/cwt",
        "name": "쌀",
        "change": "0.1650"
      },
      "sugar": {
        "price": 14.12,
        "unit": "USc/lb",
        "name": "설탕",
        "change": "0.11"
      },
      "cocoa": {
        "price": 3868,
        "unit": "USD/MT",
        "name": "코코아",
        "change": "70.00"
      },
      "corn": {
        "price": 407.6051,
        "unit": "USD/부셸",
        "name": "옥수수",
        "change": "5.1449"
      },
      "lead": {
        "price": 0.8968121490324864,
        "unit": "USD/lb",
        "name": "납",
        "change": "10.00"
      },
      "aluminum": {
        "price": 1.5711777993486407,
        "unit": "USD/lb",
        "name": "알루미늄",
        "change": "79.15"
      },
      "zinc": {
        "price": 1.6333427075867952,
        "unit": "USD/lb",
        "name": "아연",
        "change": "22.65"
      },
      "nickel": {
        "price": 8.203227767143545,
        "unit": "USD/lb",
        "name": "니켈",
        "change": "295"
      },
      "palladium": {
        "price": 1345.5,
        "unit": "USD/oz",
        "name": "팔라듐",
        "change": "54.00"
      }
    },
    "stocks": [
      {
        "code": "005930",
        "name": "삼성전자",
        "id": "samsung",
        "price": 337000,
        "timestamp": "2026-06-15T08:31:16.427Z"
      },
      {
        "code": "000660",
        "name": "SK하이닉스",
        "id": "skhynix",
        "price": 2288000,
        "timestamp": "2026-06-15T08:31:17.054Z"
      },
      {
        "code": "373220",
        "name": "LG에너지솔루션",
        "id": "lgenergy",
        "price": 420500,
        "timestamp": "2026-06-15T08:31:17.721Z"
      },
      {
        "code": "207940",
        "name": "삼성바이오로직스",
        "id": "samsungbio",
        "price": 1332000,
        "timestamp": "2026-06-15T08:31:18.406Z"
      },
      {
        "code": "005380",
        "name": "현대차",
        "id": "hyundai",
        "price": 647000,
        "timestamp": "2026-06-15T08:31:19.126Z"
      },
      {
        "code": "005490",
        "name": "POSCO홀딩스",
        "id": "posco",
        "price": 395000,
        "timestamp": "2026-06-15T08:31:19.785Z"
      },
      {
        "code": "000270",
        "name": "기아",
        "id": "kia",
        "price": 167500,
        "timestamp": "2026-06-15T08:31:20.507Z"
      },
      {
        "code": "068270",
        "name": "셀트리온",
        "id": "celltrion",
        "price": 175000,
        "timestamp": "2026-06-15T08:31:21.218Z"
      },
      {
        "code": "051910",
        "name": "LG화학",
        "id": "lgchem",
        "price": 360500,
        "timestamp": "2026-06-15T08:31:21.891Z"
      },
      {
        "code": "006400",
        "name": "삼성SDI",
        "id": "samsungsdi",
        "price": 553000,
        "timestamp": "2026-06-15T08:31:22.579Z"
      },
      {
        "code": "035420",
        "name": "NAVER",
        "id": "naver",
        "price": 248000,
        "timestamp": "2026-06-15T08:31:23.235Z"
      },
      {
        "code": "035720",
        "name": "카카오",
        "id": "kakao",
        "price": 40750,
        "timestamp": "2026-06-15T08:31:23.855Z"
      },
      {
        "code": "036570",
        "name": "NCsoft",
        "id": "ncsoft",
        "price": 261500,
        "timestamp": "2026-06-15T08:31:24.561Z"
      },
      {
        "code": "251270",
        "name": "넷마블",
        "id": "netmarble",
        "price": 41150,
        "timestamp": "2026-06-15T08:31:25.246Z"
      },
      {
        "code": "263750",
        "name": "펄어비스",
        "id": "pearlabyss",
        "price": 40000,
        "timestamp": "2026-06-15T08:31:25.934Z"
      },
      {
        "code": "055550",
        "name": "신한지주",
        "id": "shinhan",
        "price": 105600,
        "timestamp": "2026-06-15T08:31:26.632Z"
      },
      {
        "code": "105560",
        "name": "KB금융",
        "id": "kb",
        "price": 169600,
        "timestamp": "2026-06-15T08:31:27.246Z"
      },
      {
        "code": "086790",
        "name": "하나금융지주",
        "id": "hana",
        "price": 129300,
        "timestamp": "2026-06-15T08:31:27.932Z"
      },
      {
        "code": "024110",
        "name": "기업은행",
        "id": "ibk",
        "price": 22400,
        "timestamp": "2026-06-15T08:31:28.660Z"
      },
      {
        "code": "326030",
        "name": "SK바이오팜",
        "id": "skbiopharm",
        "price": 90200,
        "timestamp": "2026-06-15T08:31:29.331Z"
      },
      {
        "code": "128940",
        "name": "한미약품",
        "id": "hanmi",
        "price": 420500,
        "timestamp": "2026-06-15T08:31:30.055Z"
      },
      {
        "code": "003670",
        "name": "포스코퓨처엠",
        "id": "poscofuturem",
        "price": 210500,
        "timestamp": "2026-06-15T08:31:30.718Z"
      },
      {
        "code": "247540",
        "name": "에코프로비엠",
        "id": "ecoproBM",
        "price": 186500,
        "timestamp": "2026-06-15T08:31:31.350Z"
      },
      {
        "code": "352820",
        "name": "하이브",
        "id": "hybe",
        "price": 218500,
        "timestamp": "2026-06-15T08:31:31.957Z"
      },
      {
        "code": "035900",
        "name": "JYP Ent.",
        "id": "jyp",
        "price": 55900,
        "timestamp": "2026-06-15T08:31:32.627Z"
      },
      {
        "code": "041510",
        "name": "SM",
        "id": "sm",
        "price": 81200,
        "timestamp": "2026-06-15T08:31:33.296Z"
      },
      {
        "code": "122870",
        "name": "YG",
        "id": "yg",
        "price": 45000,
        "timestamp": "2026-06-15T08:31:33.995Z"
      },
      {
        "code": "000810",
        "name": "삼성화재",
        "id": "samsungfire",
        "price": 676000,
        "timestamp": "2026-06-15T08:31:34.746Z"
      },
      {
        "code": "066570",
        "name": "LG전자",
        "id": "lgelectronics",
        "price": 243500,
        "timestamp": "2026-06-15T08:31:35.441Z"
      },
      {
        "code": "034730",
        "name": "SK",
        "id": "sk",
        "price": 646000,
        "timestamp": "2026-06-15T08:31:36.139Z"
      },
      {
        "code": "003550",
        "name": "LG",
        "id": "lg",
        "price": 118400,
        "timestamp": "2026-06-15T08:31:36.937Z"
      }
    ]
  }
}