{
  "timestamp": "2026-04-16T18:00:16.457Z",
  "collectionTime": 73743,
  "data": {
    "exchange": {
      "usdToKrw": 1480.9,
      "eurToKrw": 1743.54,
      "jpyToKrw": 929.89,
      "cnyToKrw": 217.02,
      "timestamp": "2026-04-16"
    },
    "expandedExchange": {
      "major": {
        "usdToKrw": 1481.1,
        "eurToKrw": 1743.54,
        "jpyToKrw": 929.89,
        "cnyToKrw": 217.02,
        "gbpToKrw": 2002.92,
        "chfToKrw": 1888.06,
        "audToKrw": 1059.8,
        "cadToKrw": 1080.44
      },
      "asia": {
        "sgdToKrw": 1163,
        "hkdToKrw": 189.24,
        "twdToKrw": 46.89,
        "thbToKrw": 46.22,
        "vndToKrw": 5.64,
        "phpToKrw": 24.69,
        "myrToKrw": 374.53,
        "idrToKrw": 8.66
      },
      "units": {
        "JPY": 100,
        "VND": 100,
        "IDR": 10000
      },
      "timestamp": "2026-04-16"
    },
    "crypto": {
      "binancecoin": {
        "usd": 627.18,
        "krw": 928366,
        "change24h": "0.87",
        "marketCap": 84536405988.49321
      },
      "bitcoin": {
        "usd": 74288,
        "krw": 109962262,
        "change24h": "0.11",
        "marketCap": 1486838942127.459
      },
      "cardano": {
        "usd": 0.253079,
        "krw": 374.6,
        "change24h": "3.08",
        "marketCap": 9357984561.996864
      },
      "dogecoin": {
        "usd": 0.097732,
        "krw": 144.66,
        "change24h": "3.17",
        "marketCap": 15036001221.443161
      },
      "ethereum": {
        "usd": 2324.47,
        "krw": 3440715,
        "change24h": "-1.19",
        "marketCap": 280368775592.34906
      },
      "polkadot": {
        "usd": 1.31,
        "krw": 1943.98,
        "change24h": "11.00",
        "marketCap": 2209868604.5642786
      },
      "ripple": {
        "usd": 1.43,
        "krw": 2110.86,
        "change24h": "3.11",
        "marketCap": 87861675385.31813
      },
      "solana": {
        "usd": 86.56,
        "krw": 128128,
        "change24h": "2.10",
        "marketCap": 49825927338.76964
      }
    },
    "expandedCrypto": {
      "avalanche-2": {
        "usd": 9.53,
        "usd_market_cap": 4115245256.0885715,
        "usd_24h_vol": 340063991.5393787,
        "usd_24h_change": 0.8027047538079674,
        "krw": 14099.26,
        "krw_market_cap": 6091302587349.488,
        "krw_24h_vol": 503355825139.0957,
        "krw_24h_change": 1.0809910489184127
      },
      "binancecoin": {
        "usd": 627.18,
        "usd_market_cap": 84536405988.49321,
        "usd_24h_vol": 1192858970.7046402,
        "usd_24h_change": 0.8723041991251533,
        "krw": 928366,
        "krw_market_cap": 125129074083999.77,
        "krw_24h_vol": 1765684562352.4106,
        "krw_24h_change": 1.1305869148465335
      },
      "bitcoin": {
        "usd": 74288,
        "usd_market_cap": 1486838942127.459,
        "usd_24h_vol": 43506252194.194336,
        "usd_24h_change": 0.1127202591765485,
        "krw": 109962262,
        "krw_market_cap": 2200788854990672.5,
        "krw_24h_vol": 64398491147467.22,
        "krw_24h_change": 0.3690580663882304
      },
      "bitcoin-cash": {
        "usd": 439.8,
        "usd_market_cap": 8805616152.031664,
        "usd_24h_vol": 217859792.09997362,
        "usd_24h_change": 0.5758137501230268,
        "krw": 650983,
        "krw_market_cap": 13033894485564.166,
        "krw_24h_vol": 322471646941.2362,
        "krw_24h_change": 0.8534736666361495
      },
      "cardano": {
        "usd": 0.253079,
        "usd_market_cap": 9357984561.996864,
        "usd_24h_vol": 575985738.083341,
        "usd_24h_change": 3.084115511371397,
        "krw": 374.6,
        "krw_market_cap": 13851499006172.773,
        "krw_24h_vol": 852562410824.1357,
        "krw_24h_change": 3.3687001032279307
      },
      "chainlink": {
        "usd": 9.41,
        "usd_market_cap": 6848440070.060147,
        "usd_24h_vol": 391596143.2292764,
        "usd_24h_change": 1.8422661471533919,
        "krw": 13931.25,
        "krw_market_cap": 10136922132732.164,
        "krw_24h_vol": 579632671204.5746,
        "krw_24h_change": 2.123422362167277
      },
      "dogecoin": {
        "usd": 0.097732,
        "usd_market_cap": 15036001221.443161,
        "usd_24h_vol": 2384003398.143017,
        "usd_24h_change": 3.170795845784189,
        "krw": 144.66,
        "krw_market_cap": 22255984138019.39,
        "krw_24h_vol": 3528753491878.3916,
        "krw_24h_change": 3.455619736270467
      },
      "ethereum": {
        "usd": 2324.47,
        "usd_market_cap": 280368775592.34906,
        "usd_24h_vol": 20650993475.220642,
        "usd_24h_change": -1.1859000680295881,
        "krw": 3440715,
        "krw_market_cap": 414996176874501.2,
        "krw_24h_vol": 30567855272026.082,
        "krw_24h_change": -0.9328873676196534
      },
      "litecoin": {
        "usd": 55.81,
        "usd_market_cap": 4302180446.259335,
        "usd_24h_vol": 412287698.5781848,
        "usd_24h_change": 1.1976425105148345,
        "krw": 82613,
        "krw_market_cap": 6368000265542.335,
        "krw_24h_vol": 610259891890.0525,
        "krw_24h_change": 1.477019111340599
      },
      "monero": {
        "usd": 343.43,
        "usd_market_cap": 6338301855.53422,
        "usd_24h_vol": 104567033.39601971,
        "usd_24h_change": -1.4207072867652513,
        "krw": 508338,
        "krw_market_cap": 9381825891153.326,
        "krw_24h_vol": 154778002631.6192,
        "krw_24h_change": -1.1485591711886451
      },
      "polkadot": {
        "usd": 1.31,
        "usd_market_cap": 2209868604.5642786,
        "usd_24h_vol": 364294373.2974625,
        "usd_24h_change": 10.998515553543799,
        "krw": 1943.98,
        "krw_market_cap": 3271002701180.218,
        "krw_24h_vol": 539221144922.19086,
        "krw_24h_change": 11.30494945064602
      },
      "ripple": {
        "usd": 1.43,
        "usd_market_cap": 87861675385.31813,
        "usd_24h_vol": 3872934751.835943,
        "usd_24h_change": 3.1059145258678202,
        "krw": 2110.86,
        "krw_market_cap": 130051070422017.73,
        "krw_24h_vol": 5732765792317.723,
        "krw_24h_change": 3.3699163826917613
      },
      "shiba-inu": {
        "usd": 0.00000622,
        "usd_market_cap": 3665661173.5493274,
        "usd_24h_vol": 169238375.2224029,
        "usd_24h_change": 5.0002721081223225,
        "krw": 0.00920848,
        "krw_market_cap": 5425837344141.757,
        "krw_24h_vol": 250503211526.9047,
        "krw_24h_change": 5.29014663859172
      },
      "solana": {
        "usd": 86.56,
        "usd_market_cap": 49825927338.76964,
        "usd_24h_vol": 4186301478.259691,
        "usd_24h_change": 2.096457501257619,
        "krw": 128128,
        "krw_market_cap": 73751327376344.05,
        "krw_24h_vol": 6196615086148.724,
        "krw_24h_change": 2.3578746515678044
      },
      "stellar": {
        "usd": 0.164884,
        "usd_market_cap": 5467973185.917148,
        "usd_24h_vol": 123662201.7421061,
        "usd_24h_change": 5.31140458583877,
        "krw": 244.06,
        "krw_market_cap": 8093583041170.239,
        "krw_24h_vol": 183042283643.86285,
        "krw_24h_change": 5.602138060566901
      },
      "tether": {
        "usd": 1,
        "usd_market_cap": 185772446071.3857,
        "usd_24h_vol": 77532183375.9873,
        "usd_24h_change": 0.012359056982154662,
        "krw": 1480.49,
        "krw_market_cap": 274976607952748.66,
        "krw_24h_vol": 114764094192618.27,
        "krw_24h_change": 0.26843989015064945
      },
      "the-open-network": {
        "usd": 1.42,
        "usd_market_cap": 3535997786.781822,
        "usd_24h_vol": 131781462.50933942,
        "usd_24h_change": 4.0226610389094875,
        "krw": 2101.44,
        "krw_market_cap": 5233912228103.327,
        "krw_24h_vol": 195060248805.39032,
        "krw_24h_change": 4.309836675900053
      },
      "tron": {
        "usd": 0.32649,
        "usd_market_cap": 30959137452.572285,
        "usd_24h_vol": 533377913.10631156,
        "usd_24h_change": -0.4034482120255609,
        "krw": 483.26,
        "krw_market_cap": 45825087529826.49,
        "krw_24h_vol": 789495172209.396,
        "krw_24h_change": -0.1284917466158137
      },
      "uniswap": {
        "usd": 3.37,
        "usd_market_cap": 2135763361.5084648,
        "usd_24h_vol": 221458618.62592906,
        "usd_24h_change": 4.7174236400009315,
        "krw": 4987.67,
        "krw_market_cap": 3161313622966.9106,
        "krw_24h_vol": 327798556995.14886,
        "krw_24h_change": 4.983238784781354
      }
    },
    "kospi": {
      "value": 6226.05,
      "change": "2.21",
      "changeAmount": "134.66",
      "timestamp": "2026-04-16T18:00:35.123Z",
      "source": "yahoo"
    },
    "kosdaq": {
      "value": 1162.97,
      "change": "3.66",
      "changeAmount": "41.09",
      "timestamp": "2026-04-16T18:00:35.063Z",
      "source": "yahoo"
    },
    "nasdaq": null,
    "globalIndices": {
      "kospi": {
        "name": "KOSPI",
        "value": 6226.05,
        "previousClose": 6226.05,
        "change": "-0.36",
        "symbol": "KOSPI:KRX",
        "source": "google"
      },
      "n225": {
        "name": "닛케이 225",
        "value": 59518.34,
        "previousClose": 59518.34,
        "change": "-0.33",
        "symbol": "NI225:INDEXNIKKEI",
        "source": "google"
      },
      "000001ss": {
        "name": "상해종합",
        "value": 4055.5469,
        "previousClose": 4055.5469,
        "change": "-0.37",
        "symbol": "000001:SHA",
        "source": "google"
      },
      "hsi": {
        "name": "항셍지수",
        "value": 26394.26,
        "previousClose": 26394.26,
        "change": "-0.37",
        "symbol": "HSI:INDEXHANGSENG",
        "source": "google"
      },
      "ftse": {
        "name": "FTSE 100",
        "value": 10589.99,
        "previousClose": 10589.99,
        "change": "-0.37",
        "symbol": "UKX:INDEXFTSE",
        "source": "google"
      },
      "gdaxi": {
        "name": "DAX",
        "value": 24154.47,
        "previousClose": 24154.47,
        "change": "-0.37",
        "symbol": "DAX:INDEXDB",
        "source": "google"
      },
      "fchi": {
        "name": "CAC 40",
        "value": 8262.7,
        "previousClose": 8262.7,
        "change": "-0.37",
        "symbol": "PX1:INDEXEURO",
        "source": "google"
      },
      "dji": {
        "name": "다우존스",
        "value": 48527.73,
        "previousClose": 48463.72,
        "change": "0.00",
        "symbol": "DJI",
        "source": "naver"
      },
      "nasdaq": {
        "name": "나스닥",
        "value": 24093.31,
        "previousClose": 24016.02,
        "change": "0.00",
        "symbol": "NASDAQ",
        "source": "naver"
      },
      "gspc": {
        "name": "S&P 500",
        "value": 7037.05,
        "previousClose": 7022.95,
        "change": "0.00",
        "symbol": "GSPC",
        "source": "naver"
      },
      "rut": {
        "name": "러셀 2000",
        "value": 2711.0266,
        "previousClose": 2713.6633,
        "change": "-0.10",
        "symbol": "^RUT",
        "source": "yahoo"
      }
    },
    "commodities": {
      "gold": {
        "price": 4787.61,
        "unit": "USD/oz",
        "change": "2.41"
      },
      "silver": {
        "price": 78.276,
        "unit": "USD/oz",
        "change": "0.681"
      },
      "copper": {
        "price": 6.0577,
        "unit": "USD/lb",
        "change": "0.0143"
      },
      "oil": {
        "wti": null,
        "brent": 99.561,
        "unit": "USD/bbl",
        "change": "4.631"
      }
    },
    "expandedCommodities": {
      "oil_brent": {
        "price": 99.561,
        "unit": "USD/bbl",
        "name": "브렌트유",
        "change": "4.631"
      },
      "gasoline": {
        "price": 3.1496,
        "unit": "USD/gal",
        "name": "휘발유",
        "change": "0.0804"
      },
      "gold": {
        "price": 4787.61,
        "unit": "USD/oz",
        "name": "금",
        "change": "2.41"
      },
      "silver": {
        "price": 78.276,
        "unit": "USD/oz",
        "name": "은",
        "change": "0.681"
      },
      "copper": {
        "price": 6.0577,
        "unit": "USD/lb",
        "name": "구리",
        "change": "0.0143"
      },
      "platinum": {
        "price": 2105.9,
        "unit": "USD/oz",
        "name": "백금",
        "change": "24.60"
      },
      "soybeans": {
        "price": 1162.84,
        "unit": "USD/부셸",
        "name": "대두",
        "change": "4.16"
      },
      "wheat": {
        "price": 596.69,
        "unit": "USD/부셸",
        "name": "밀",
        "change": "2.94"
      },
      "coffee": {
        "price": 290.6,
        "unit": "USc/lb",
        "name": "커피",
        "change": "7.65"
      },
      "cotton": {
        "price": 77.993,
        "unit": "USc/lb",
        "name": "면화",
        "change": "0.573"
      },
      "rice": {
        "price": 10.851,
        "unit": "USD/cwt",
        "name": "쌀",
        "change": "0.0540"
      },
      "sugar": {
        "price": 13.82,
        "unit": "USc/lb",
        "name": "설탕",
        "change": "0.12"
      },
      "cocoa": {
        "price": 3506,
        "unit": "USD/MT",
        "name": "코코아",
        "change": "57.00"
      },
      "corn": {
        "price": 447.9458,
        "unit": "USD/부셸",
        "name": "옥수수",
        "change": "3.3042"
      },
      "lead": {
        "price": 0.88632054503724,
        "unit": "USD/lb",
        "name": "납",
        "change": "14.15"
      },
      "aluminum": {
        "price": 1.653096678792717,
        "unit": "USD/lb",
        "name": "알루미늄",
        "change": "24.30"
      },
      "zinc": {
        "price": 1.5537144723353684,
        "unit": "USD/lb",
        "name": "아연",
        "change": "28.10"
      },
      "nickel": {
        "price": 8.289410419936315,
        "unit": "USD/lb",
        "name": "니켈",
        "change": "35"
      },
      "palladium": {
        "price": 1571.5,
        "unit": "USD/oz",
        "name": "팔라듐",
        "change": "17.00"
      }
    },
    "stocks": [
      {
        "code": "005930",
        "name": "삼성전자",
        "id": "samsung",
        "price": 217500,
        "timestamp": "2026-04-16T18:01:08.951Z"
      },
      {
        "code": "000660",
        "name": "SK하이닉스",
        "id": "skhynix",
        "price": 1155000,
        "timestamp": "2026-04-16T18:01:09.640Z"
      },
      {
        "code": "373220",
        "name": "LG에너지솔루션",
        "id": "lgenergy",
        "price": 416000,
        "timestamp": "2026-04-16T18:01:10.340Z"
      },
      {
        "code": "207940",
        "name": "삼성바이오로직스",
        "id": "samsungbio",
        "price": 1616000,
        "timestamp": "2026-04-16T18:01:11.020Z"
      },
      {
        "code": "005380",
        "name": "현대차",
        "id": "hyundai",
        "price": 534000,
        "timestamp": "2026-04-16T18:01:11.700Z"
      },
      {
        "code": "005490",
        "name": "POSCO홀딩스",
        "id": "posco",
        "price": 370000,
        "timestamp": "2026-04-16T18:01:12.413Z"
      },
      {
        "code": "000270",
        "name": "기아",
        "id": "kia",
        "price": 157900,
        "timestamp": "2026-04-16T18:01:13.144Z"
      },
      {
        "code": "068270",
        "name": "셀트리온",
        "id": "celltrion",
        "price": 209000,
        "timestamp": "2026-04-16T18:01:13.866Z"
      },
      {
        "code": "051910",
        "name": "LG화학",
        "id": "lgchem",
        "price": 357500,
        "timestamp": "2026-04-16T18:01:14.570Z"
      },
      {
        "code": "006400",
        "name": "삼성SDI",
        "id": "samsungsdi",
        "price": 478500,
        "timestamp": "2026-04-16T18:01:15.270Z"
      },
      {
        "code": "035420",
        "name": "NAVER",
        "id": "naver",
        "price": 218500,
        "timestamp": "2026-04-16T18:01:15.975Z"
      },
      {
        "code": "035720",
        "name": "카카오",
        "id": "kakao",
        "price": 50600,
        "timestamp": "2026-04-16T18:01:16.680Z"
      },
      {
        "code": "036570",
        "name": "NCsoft",
        "id": "ncsoft",
        "price": 266500,
        "timestamp": "2026-04-16T18:01:17.376Z"
      },
      {
        "code": "251270",
        "name": "넷마블",
        "id": "netmarble",
        "price": 51900,
        "timestamp": "2026-04-16T18:01:18.080Z"
      },
      {
        "code": "263750",
        "name": "펄어비스",
        "id": "pearlabyss",
        "price": 55300,
        "timestamp": "2026-04-16T18:01:18.756Z"
      },
      {
        "code": "055550",
        "name": "신한지주",
        "id": "shinhan",
        "price": 99900,
        "timestamp": "2026-04-16T18:01:19.478Z"
      },
      {
        "code": "105560",
        "name": "KB금융",
        "id": "kb",
        "price": 162300,
        "timestamp": "2026-04-16T18:01:20.177Z"
      },
      {
        "code": "086790",
        "name": "하나금융지주",
        "id": "hana",
        "price": 122500,
        "timestamp": "2026-04-16T18:01:20.990Z"
      },
      {
        "code": "024110",
        "name": "기업은행",
        "id": "ibk",
        "price": 22850,
        "timestamp": "2026-04-16T18:01:21.712Z"
      },
      {
        "code": "326030",
        "name": "SK바이오팜",
        "id": "skbiopharm",
        "price": 106400,
        "timestamp": "2026-04-16T18:01:22.468Z"
      },
      {
        "code": "128940",
        "name": "한미약품",
        "id": "hanmi",
        "price": 528000,
        "timestamp": "2026-04-16T18:01:23.157Z"
      },
      {
        "code": "003670",
        "name": "포스코퓨처엠",
        "id": "poscofuturem",
        "price": 223500,
        "timestamp": "2026-04-16T18:01:23.828Z"
      },
      {
        "code": "247540",
        "name": "에코프로비엠",
        "id": "ecoproBM",
        "price": 205000,
        "timestamp": "2026-04-16T18:01:24.589Z"
      },
      {
        "code": "352820",
        "name": "하이브",
        "id": "hybe",
        "price": 268000,
        "timestamp": "2026-04-16T18:01:25.298Z"
      },
      {
        "code": "035900",
        "name": "JYP Ent.",
        "id": "jyp",
        "price": 63000,
        "timestamp": "2026-04-16T18:01:25.994Z"
      },
      {
        "code": "041510",
        "name": "SM",
        "id": "sm",
        "price": 97000,
        "timestamp": "2026-04-16T18:01:26.694Z"
      },
      {
        "code": "122870",
        "name": "YG",
        "id": "yg",
        "price": 55500,
        "timestamp": "2026-04-16T18:01:27.378Z"
      },
      {
        "code": "000810",
        "name": "삼성화재",
        "id": "samsungfire",
        "price": 490000,
        "timestamp": "2026-04-16T18:01:28.089Z"
      },
      {
        "code": "066570",
        "name": "LG전자",
        "id": "lgelectronics",
        "price": 126000,
        "timestamp": "2026-04-16T18:01:28.808Z"
      },
      {
        "code": "034730",
        "name": "SK",
        "id": "sk",
        "price": 371000,
        "timestamp": "2026-04-16T18:01:29.497Z"
      },
      {
        "code": "003550",
        "name": "LG",
        "id": "lg",
        "price": 93800,
        "timestamp": "2026-04-16T18:01:30.200Z"
      }
    ]
  }
}